{
  "THE_ARCHITECT.talk.WATCHER-WATCHER.0-0.char": "[sine]我前来评估这座高塔。\n也为寻找那个消失于其中的人。[/sine]",
  "THE_ARCHITECT.talk.WATCHER-WATCHER.0-0.next": "继续",
  "THE_ARCHITECT.talk.WATCHER-WATCHER.0-1.ancient": "评估？我在此维持秩序。没有什么可评估的。",
  "THE_ARCHITECT.talk.WATCHER-WATCHER.0-1.next": "回答",
  "THE_ARCHITECT.talk.WATCHER-WATCHER.0-2.char": "[jitter]那由我来评判。不是你。[/jitter]",
  "THE_ARCHITECT.talk.WATCHER-WATCHER.1-0r.ancient": "观者又回来了。你的教团除了固执，难道什么也不教么？",
  "THE_ARCHITECT.talk.WATCHER-WATCHER.1-0r.next": "回应",
  "THE_ARCHITECT.talk.WATCHER-WATCHER.1-1r.char": "[sine]它教导忍耐。而我的忍耐已经枯竭。[/sine]",
  "THE_ARCHITECT.talk.WATCHER-WATCHER.1-1r.next": "继续",
  "THE_ARCHITECT.talk.WATCHER-WATCHER.1-2r.ancient": "那就了结此事吧。",
  "THE_ARCHITECT.talk.WATCHER-WATCHER.2-0r.ancient": "你竟敢对我作出评判？",
  "THE_ARCHITECT.talk.WATCHER-WATCHER.2-0r.next": "回答",
  "THE_ARCHITECT.talk.WATCHER-WATCHER.2-1r.char": "[jitter]我已经评判了。裁决将至。[/jitter]",
  "THE_ARCHITECT.talk.WATCHER-WATCHER.2-1r.next": "继续",
  "THE_ARCHITECT.talk.WATCHER-WATCHER.2-2r.ancient": "[jitter][red]够了！[/red][/jitter]",

  "DARV.talk.WATCHER-WATCHER.0-0.ancient": "哎呀，你可真是个善于观察的！安静又不动，好像在掂量我这儿的每一件破烂似的。",
  "DARV.talk.WATCHER-WATCHER.0-0.next": "回应",
  "DARV.talk.WATCHER-WATCHER.0-1.char": "[sine]我衡量万物。这是我的使命。让我看看你的货物。[/sine]",
  "DARV.talk.WATCHER-WATCHER.0-1.next": "继续",
  "DARV.talk.WATCHER-WATCHER.0-2.ancient": "哈！一位有礼貌的顾客！来瞧瞧那堆东西吧！",
  "DARV.talk.WATCHER-WATCHER.1-0r.ancient": "又回来啦，平静得像一汪静水。需要什么就拿吧！",
  "DARV.talk.WATCHER-WATCHER.2-0.ancient": "在那堆里翻到了这本旧日志。是另一个和你一样的人的，也是善于观察、安静的那种。",
  "DARV.talk.WATCHER-WATCHER.2-0.next": "回应",
  "DARV.talk.WATCHER-WATCHER.2-1.char": "[sine]那是我同道之人的东西。你在哪里找到的？[/sine]",
  "DARV.talk.WATCHER-WATCHER.2-1.next": "继续",
  "DARV.talk.WATCHER-WATCHER.2-2.ancient": "不知道呀！东西总会兜兜转转来到我这堆里。拿去吧，好好用上！",

  "NEOW.talk.WATCHER-WATCHER.0-0.ancient": "[sine]...观者... ..你.. 知晓.. ..这轮回.. ..如同.. ..我...[/sine]",
  "NEOW.talk.WATCHER-WATCHER.0-0.next": "继续",
  "NEOW.talk.WATCHER-WATCHER.0-1.char": "[sine]我只是前来观看。仅此而已。[/sine]",
  "NEOW.talk.WATCHER-WATCHER.0-1.next": "继续",
  "NEOW.talk.WATCHER-WATCHER.0-2.ancient": "[sine]...那么.. 注视.. [red][jitter]建筑师[/jitter][/red]..\n..然后.. 终结.. 他...[/sine]",
  "NEOW.talk.WATCHER-WATCHER.1-0r.ancient": "[sine]..仍在.. 观看... ..很好...[/sine]",
  "NEOW.talk.WATCHER-WATCHER.2-0.ancient": "[sine]..你.. 前来.. ..评判... ..如同.. ..我...[/sine]",
  "NEOW.talk.WATCHER-WATCHER.2-0.next": "回答",
  "NEOW.talk.WATCHER-WATCHER.2-1.char": "[sine]是评估，而非定罪。\n你早已决断。我尚未。[/sine]",
  "NEOW.talk.WATCHER-WATCHER.2-1.next": "继续",
  "NEOW.talk.WATCHER-WATCHER.2-2.ancient": "[sine]...裁决.. ..早已.. ..写就...[/sine]",

  "NONUPEIPE.talk.WATCHER-WATCHER.0-0.ancient": "一位朝圣者，宁静而从容。多么雅致呀！\n过来一些，接受我的赐福吧。",
  "NONUPEIPE.talk.WATCHER-WATCHER.0-0.next": "上前",
  "NONUPEIPE.talk.WATCHER-WATCHER.0-1.char": "[sine]我不需要华饰。但我不会拒绝道路所赠予的。[/sine]",
  "NONUPEIPE.talk.WATCHER-WATCHER.0-1.next": "继续",
  "NONUPEIPE.talk.WATCHER-WATCHER.0-2.ancient": "睿智又谦逊！真是位难得的访客呢。",
  "NONUPEIPE.talk.WATCHER-WATCHER.1-0r.ancient": "宁静之人又回来了。穿戴上这些礼物吧，旅人。",
  "NONUPEIPE.talk.WATCHER-WATCHER.2-0.ancient": "你周身如此宁静……可我却感到其下藏着一场风暴。你究竟是哪一面呢？",
  "NONUPEIPE.talk.WATCHER-WATCHER.2-0.next": "回答",
  "NONUPEIPE.talk.WATCHER-WATCHER.2-1.char": "我是[sine]平静[/sine]，亦是[jitter]愤怒[/jitter]。\n二者皆然，视当下所需而定。",
  "NONUPEIPE.talk.WATCHER-WATCHER.2-1.next": "继续",
  "NONUPEIPE.talk.WATCHER-WATCHER.2-2.ancient": "多么令人激动！那就将我的赐福带入这两种姿态吧。",

  "OROBAS.talk.WATCHER-WATCHER.0-0.ancient": "好安静！！好不动！！不拿亮闪闪的？？为什么为什么？？奇怪的家伙！！",
  "OROBAS.talk.WATCHER-WATCHER.0-0.next": "回应",
  "OROBAS.talk.WATCHER-WATCHER.0-1.char": "[sine]我只取所需之物。我前来观看，而非收集。[/sine]",
  "OROBAS.talk.WATCHER-WATCHER.0-1.next": "继续",
  "OROBAS.talk.WATCHER-WATCHER.0-2.ancient": "观看观看！！好吧！但还是拿上亮闪闪的！拿走拿走！",
  "OROBAS.talk.WATCHER-WATCHER.1-0r.ancient": "安静朋友回来了！！找到漂亮东西！你看你看！",
  "OROBAS.talk.WATCHER-WATCHER.2-0.ancient": "有时候会生气？吓人地生气？？不要不要！！一直平静！！",
  "OROBAS.talk.WATCHER-WATCHER.2-0.next": "回答",
  "OROBAS.talk.WATCHER-WATCHER.2-1.char": "[jitter]愤怒自有其用处。[/jitter] [sine]平和亦然。二者我皆持守。[/sine]",
  "OROBAS.talk.WATCHER-WATCHER.2-1.next": "继续",
  "OROBAS.talk.WATCHER-WATCHER.2-2.ancient": "好困惑！！不过……好吧！大部分时候平静！！大部分！！",

  "PAEL.talk.WATCHER-WATCHER.0-0.ancient": "[thinky_dots]寻求宁静之人……我们很相似。歇息吧，拿走我的一部分……[/thinky_dots]",
  "PAEL.talk.WATCHER-WATCHER.0-0.next": "回答",
  "PAEL.talk.WATCHER-WATCHER.0-1.char": "[sine]你的宁静是沉睡。我的宁静是觉醒。我们并不相似。[/sine]",
  "PAEL.talk.WATCHER-WATCHER.0-1.next": "继续",
  "PAEL.talk.WATCHER-WATCHER.0-2.ancient": "[thinky_dots]或许不像吧……但还是拿走这个吧……[/thinky_dots]",
  "PAEL.talk.WATCHER-WATCHER.1-0r.ancient": "[thinky_dots]安静之人又回来了。坐下，呼吸，让这世界变得柔和……[/thinky_dots]",
  "PAEL.talk.WATCHER-WATCHER.2-0.ancient": "[thinky_dots]你的安宁是如此……锋利。难道它从不会变钝么……？[/thinky_dots]",
  "PAEL.talk.WATCHER-WATCHER.2-0.next": "回答",
  "PAEL.talk.WATCHER-WATCHER.2-1.char": "[sine]宁静并非屈服。我让心绪平息，是为了行动，而非随波逐流。[/sine]",
  "PAEL.talk.WATCHER-WATCHER.2-1.next": "继续",
  "PAEL.talk.WATCHER-WATCHER.2-2.ancient": "[thinky_dots]……多么不得安歇的一种平静啊……[/thinky_dots]",

  "TANX.talk.WATCHER-WATCHER.0-0.ancient": "[b]只是根棍子！？一根普通的法杖！？刀刃在哪儿！？？[/b]",
  "TANX.talk.WATCHER-WATCHER.0-0.next": "回答",
  "TANX.talk.WATCHER-WATCHER.0-1.char": "[jitter]我的法杖已经足够。刀刃只会拖慢我。[/jitter]",
  "TANX.talk.WATCHER-WATCHER.0-1.next": "继续",
  "TANX.talk.WATCHER-WATCHER.0-2.ancient": "[b]使法杖的！？不落俗套！！强大！！我喜欢！！[/b]",
  "TANX.talk.WATCHER-WATCHER.1-0r.ancient": "[b]还是那根普通法杖！？也拿上一件真正的武器吧！！以防万一！！[/b]",
  "TANX.talk.WATCHER-WATCHER.2-0.ancient": "[b]观者，与我一战！！[/b]",
  "TANX.talk.WATCHER-WATCHER.2-0.next": "回绝",
  "TANX.talk.WATCHER-WATCHER.2-1.char": "[sine]我不会无故而战。你并非敌人。[/sine]",
  "TANX.talk.WATCHER-WATCHER.2-1.next": "继续",
  "TANX.talk.WATCHER-WATCHER.2-2.ancient": "[b]那我就给你个理由！！与我一战！！[/b]",

  "TEZCATARA.talk.WATCHER-WATCHER.0-0.ancient": "过来一些，亲爱的。我的眼神不太好使，但我能闻到你内心深藏的那团[jitter][b]火[/b][/jitter]。",
  "TEZCATARA.talk.WATCHER-WATCHER.0-0.next": "什么也不说",
  "TEZCATARA.talk.WATCHER-WATCHER.0-1.char": "[sine]你无需看见我。我已听见你那份慈祥之下所隐藏的东西。[/sine]",
  "TEZCATARA.talk.WATCHER-WATCHER.0-1.next": "继续",
  "TEZCATARA.talk.WATCHER-WATCHER.0-2.ancient": "哦？小观者把我看穿了呢。让我来给你那[jitter][b]火焰[/b][/jitter]添些柴火吧，亲爱的。",
  "TEZCATARA.talk.WATCHER-WATCHER.1-0r.ancient": "这么快就回来啦，小可爱？坐下来，[jitter][b]闷烧[/b][/jitter]一会儿吧。我[jitter][b]坚持[/b][/jitter]哦。",
  "TEZCATARA.talk.WATCHER-WATCHER.2-0.ancient": "那颗安静的心里藏着这么多余烬呢。难道不愿让它们[jitter][b]熊熊燃烧[/b][/jitter]么？",
  "TEZCATARA.talk.WATCHER-WATCHER.2-0.next": "回答",
  "TEZCATARA.talk.WATCHER-WATCHER.2-1.char": "[sine]我的[jitter]愤怒[/jitter]由我自己点燃。不容你来添柴。[/sine]",
  "TEZCATARA.talk.WATCHER-WATCHER.2-1.next": "继续",
  "TEZCATARA.talk.WATCHER-WATCHER.2-2.ancient": "哈！这么[jitter][b]美味[/b][/jitter]的燃料，却任它[jitter][b]挨饿[/b][/jitter]。真可惜呀，小可爱。",

  "VAKUU.talk.WATCHER-WATCHER.0-0.ancient": "某个被遗忘之神的信徒么？我能提供[sine]更好[/sine]的神祇哦。",
  "VAKUU.talk.WATCHER-WATCHER.0-0.next": "对话",
  "VAKUU.talk.WATCHER-WATCHER.0-1.char": "[sine]我不侍奉任何神祇，只忠于我的使命。你的契约于我而言一文不值。[/sine]",
  "VAKUU.talk.WATCHER-WATCHER.0-1.next": "继续",
  "VAKUU.talk.WATCHER-WATCHER.0-2.ancient": "那就看着[sine]这个[/sine]吧。签下名字，见证真正的力量。",
  "VAKUU.talk.WATCHER-WATCHER.1-0r.ancient": "还在冥思我的契约么？",
  "VAKUU.talk.WATCHER-WATCHER.2-0.ancient": "你将恶魔与神祇一视同仁地评估。告诉我，小修行者……又是谁来评估[sine]你[/sine]呢？",
  "VAKUU.talk.WATCHER-WATCHER.2-0.next": "回答",
  "VAKUU.talk.WATCHER-WATCHER.2-1.char": "[jitter]我自己。[/jitter] [sine]而我从不宽纵。[/sine]",
  "VAKUU.talk.WATCHER-WATCHER.2-1.next": "继续",
  "VAKUU.talk.WATCHER-WATCHER.2-2.ancient": "[i][font_size=22][sine]真无趣。[/sine][/font_size][/i]\n签字，要么就走吧。"
}